COA/A1/4/full.v
//Full Adder. Using the HA module from the previous question, Implement a combinational full adder (FA).

module FA(S,C,a,b,c);

    output wire S,C;
    input wire a,b,c;
    wire firstSum,firstCarry,secondcarry;
   
    HA firstHalf(firstSum,firstCarry,a,b);
    HA secondHalf(S,secondcarry,firstSum,c);
    assign C = secondcarry|firstCarry;

endmodule

module HA(S,C,a,b);    
    output reg S,C;
    input wire a,b;
    always @ (a or b)
        begin
            S=a^b;
            C=a&b;
        end
endmodule

COA/A1/4/t_full.v
`timescale 1ns/100ps
module full();
    wire S,C;
    reg[2:0] inp;
    FA myAdder(S,C,inp[2],inp[1],inp[0]);
    initial 
    begin
        $dumpfile("full.vcd");
        $dumpvars(0,full);
        $display("A B C | C S\n-----------");     

        inp=3'b000;
        repeat(8)
            #10 inp=inp+1'b1;   
        #10;
        $finish;
    end

    initial
        begin
            $monitor("%b %b %b | %b %b",inp[2],inp[1],inp[0],C,S);
        end
endmodule

COA/A1/4/full.vcd
$date
	Mon Oct 16 16:30:32 2017
$end
$version
	Icarus Verilog
$end
$timescale
	100ps
$end
$scope module full $end
$var wire 1 ! C $end
$var wire 1 " S $end
$var reg 3 # inp [2:0] $end
$scope module myAdder $end
$var wire 1 ! C $end
$var wire 1 " S $end
$var wire 1 $ a $end
$var wire 1 % b $end
$var wire 1 & c $end
$var wire 1 ' firstCarry $end
$var wire 1 ( firstSum $end
$var wire 1 ) secondcarry $end
$scope module firstHalf $end
$var wire 1 $ a $end
$var wire 1 % b $end
$var reg 1 * C $end
$var reg 1 + S $end
$upscope $end
$scope module secondHalf $end
$var wire 1 ( a $end
$var wire 1 & b $end
$var reg 1 , C $end
$var reg 1 - S $end
$upscope $end
$upscope $end
$upscope $end
$enddefinitions $end
#0
$dumpvars
0-
0,
0+
0*
0)
0(
0'
0&
0%
0$
b0 #
0"
0!
$end
#100
1-
1"
1&
b1 #
#200
1+
1(
1-
1"
1%
0&
b10 #
#300
1!
1,
1)
0-
0"
1&
b11 #
#400
0!
0,
0)
1-
1"
1$
0%
0&
b100 #
#500
1!
1,
1)
0-
0"
1&
b101 #
#600
1*
1'
0+
0(
0,
0)
0-
0"
1%
0&
b110 #
#700
1-
1"
1&
b111 #
#800
0!
0*
0'
0-
0"
0$
0%
0&
b0 #
