COA/A2/2/reg.v
/*
------------------------------------------------------
            Praveen Kumar Gupta  -  16CO235
            Durvesh Bhalekar     -  16CO210
------------------------------------------------------
           32-bit Register FILE using D Flip Flops
------------------------------------------------------

*/

module RF(clk,reg1,reg2,writereg,write,data,read1,read2);
    input [4:0] reg1,reg2,writereg;
    input write,clk;
    input [31:0] data;
    output reg [31:0] read1, read2;
    reg [31:0] REG [0:31];
    always @(posedge clk)
    begin
        if(write)
            begin
                REG[writereg]  <= data;
            end
        read1 <= REG[reg1];
        read2 <= REG[reg2];  
            
    end
    
endmodule


module REG(input [31:0] data,input clk,output [31:0]out);
    genvar i;    
    generate
    for(i=0;i<32;i=i+1)
        begin : Register_Bits
          DFF flipBro(data[i],clk,out[i]);
        end
    endgenerate
endmodule

module DFF(d,clk,q);
    output reg q;
    input d,clk;
    
    initial 
      q = 1'b0;//Initialises once    
    always @ (posedge clk)
        q <= d;

endmodule

COA/A2/2/t_reg.v
/*
------------------------------------------------------
            Praveen Kumar Gupta  -  16CO235
            Durvesh Bhalekar     -  16CO210
------------------------------------------------------
Testbench for 32-bit Register FILE using D Flip Flops
------------------------------------------------------

*/

`timescale 1ns/100ps

module t_reg;

reg clk,write;
reg [4:0] reg1,reg2,writereg;
reg [31:0] data;
wire [31:0] read1,read2;

RF registerFile(clk,reg1,reg2,writereg,write,data,read1,read2);

initial
begin
    $dumpfile("regWave.vcd");
    $dumpvars(0,t_reg);
    $display("Time\twrite\twritereg\tdata\treg1\treg2\t\tread1\t\tread2\n=======================================================================================");
end
initial
    begin
        #2;
        clk=1'b0;
        repeat(100)
            begin
                #5;
                write = $random % 2;
                data = $urandom % 1000;
                writereg = $random % 5;
                reg1 = $random % 5;
                reg2 = $random % 5;
            end

        $finish;
        
    end

initial
    forever
        #5 clk = ~clk;

initial
    $monitor("%g ns\t%b\t%d\t%d\t%d\t%d\t%d\t%d",$time,write,writereg,data,reg1,reg2,read1,read2);
endmodule

COA/A2/2/regWave.vcd
$date
	Mon Oct 30 23:00:37 2017
$end
$version
	Icarus Verilog
$end
$timescale
	100ps
$end
$scope module t_reg $end
$var wire 32 ! read1 [31:0] $end
$var wire 32 " read2 [31:0] $end
$var reg 1 # clk $end
$var reg 32 $ data [31:0] $end
$var reg 5 % reg1 [4:0] $end
$var reg 5 & reg2 [4:0] $end
$var reg 1 ' write $end
$var reg 5 ( writereg [4:0] $end
$scope module registerFile $end
$var wire 1 ) clk $end
$var wire 32 * data [31:0] $end
$var wire 5 + reg1 [4:0] $end
$var wire 5 , reg2 [4:0] $end
$var wire 1 - write $end
$var wire 5 . writereg [4:0] $end
$var reg 32 / read1 [31:0] $end
$var reg 32 0 read2 [31:0] $end
$upscope $end
$upscope $end
$enddefinitions $end
#0
$dumpvars
bx 0
bx /
bx .
x-
bx ,
bx +
bx *
x)
bx (
x'
bx &
bx %
bx $
x#
bx "
bx !
$end
#20
0#
0)
#50
1#
1)
#70
b11100 &
b11100 ,
b11100 %
b11100 +
b11100 (
b11100 .
b110001100 $
b110001100 *
0'
0-
#100
0#
0)
#120
b11111 %
b11111 +
b10 (
b10 .
b111000001 $
b111000001 *
1'
1-
#150
1#
1)
#170
b10 &
b10 ,
b11 %
b11 +
b100 (
b100 .
b110011001 $
b110011001 *
#200
0#
0)
#220
b0 &
b0 ,
b100 %
b100 +
b10 (
b10 .
b101010011 $
b101010011 *
#250
1#
1)
#270
b11111 &
b11111 ,
b0 %
b0 +
b11100 (
b11100 .
b1001011101 $
b1001011101 *
#300
0#
0)
#320
b1 %
b1 +
b100 (
b100 .
0'
0-
#350
1#
1)
#370
b11101 &
b11101 ,
b100 %
b100 +
b11101 (
b11101 .
b1010100101 $
b1010100101 *
#400
0#
0)
#420
b0 &
b0 ,
b11101 %
b11101 +
b11110 (
b11110 .
b110110010 $
b110110010 *
1'
1-
#450
1#
1)
#470
b100 %
b100 +
b1 (
b1 .
b1001 $
b1001 *
0'
0-
#500
0#
0)
#520
b11101 &
b11101 ,
b0 %
b0 +
b0 (
b0 .
b1010100101 $
b1010100101 *
#550
1#
1)
#570
b11100 &
b11100 ,
b11101 %
b11101 +
b11111 (
b11111 .
b1111000110 $
b1111000110 *
1'
1-
#600
0#
0)
#620
b0 &
b0 ,
b10 %
b10 +
b11110 (
b11110 .
b11110101 $
b11110101 *
#650
b101010011 /
b101010011 !
1#
1)
#670
b1 %
b1 +
b11101 (
b11101 .
b100010101 $
b100010101 *
0'
0-
#700
0#
0)
#720
b11110 &
b11110 ,
b0 %
b0 +
b11110 (
b11110 .
b100000100 $
b100000100 *
1'
1-
#750
b11110101 0
b11110101 "
bx /
bx !
1#
1)
#770
b1 &
b1 ,
b1 %
b1 +
b1 (
b1 .
b1110101001 $
b1110101001 *
#800
0#
0)
#820
b11101 &
b11101 ,
b11101 %
b11101 +
b100 (
b100 .
b100010110 $
b100010110 *
0'
0-
#850
bx 0
bx "
1#
1)
#870
b100 &
b100 ,
b0 %
b0 +
b0 (
b0 .
b1000100101 $
b1000100101 *
1'
1-
#900
0#
0)
#920
b1 &
b1 ,
b11 %
b11 +
b1 (
b1 .
b111011010 $
b111011010 *
0'
0-
#950
1#
1)
#970
b0 &
b0 ,
b100 %
b100 +
b11 (
b11 .
b1000010101 $
b1000010101 *
#1000
0#
0)
#1020
b11110 &
b11110 ,
b11101 %
b11101 +
b11101 (
b11101 .
b1001011111 $
b1001011111 *
#1050
b100000100 0
b100000100 "
1#
1)
#1070
b11100 &
b11100 ,
b0 %
b0 +
b10 (
b10 .
b1000100010 $
b1000100010 *
1'
1-
#1100
0#
0)
#1120
b100 &
b100 ,
b11111 (
b11111 .
b1010101111 $
b1010101111 *
#1150
bx 0
bx "
1#
1)
#1170
b0 &
b0 ,
b100 (
b100 .
b1001111010 $
b1001111010 *
0'
0-
#1200
0#
0)
#1220
b11 &
b11 ,
b1 %
b1 +
b11100 (
b11100 .
b1100110 $
b1100110 *
#1250
1#
1)
#1270
b11110 &
b11110 ,
b11 %
b11 +
b11111 (
b11111 .
b1000001000 $
b1000001000 *
1'
1-
#1300
0#
0)
#1320
b0 &
b0 ,
b11101 %
b11101 +
b11 (
b11 .
b1001011101 $
b1001011101 *
#1350
1#
1)
#1370
b11110 %
b11110 +
b11101 (
b11101 .
b1000010100 $
b1000010100 *
0'
0-
#1400
0#
0)
#1420
b0 %
b0 +
b1101001101 $
b1101001101 *
#1450
1#
1)
#1470
b1 &
b1 ,
b11100 %
b11100 +
b11100 (
b11100 .
b1111010101 $
b1111010101 *
1'
1-
#1500
0#
0)
#1520
b100 &
b100 ,
b11101 %
b11101 +
b0 (
b0 .
b10001101 $
b10001101 *
#1550
1#
1)
#1570
b11111 &
b11111 ,
b0 %
b0 +
b11110 (
b11110 .
b1101101011 $
b1101101011 *
#1600
0#
0)
#1620
b1 &
b1 ,
b10 %
b10 +
b11111 (
b11111 .
b1110101010 $
b1110101010 *
#1650
b101010011 /
b101010011 !
1#
1)
#1670
b100 &
b100 ,
b0 %
b0 +
b11 (
b11 .
b100011000 $
b100011000 *
0'
0-
#1700
0#
0)
#1720
b11101 &
b11101 ,
b11110 %
b11110 +
b0 (
b0 .
b10111000 $
b10111000 *
#1750
b100000100 /
b100000100 !
1#
1)
#1770
b11110 &
b11110 ,
b11100 %
b11100 +
b1 (
b1 .
b10100010 $
b10100010 *
#1800
0#
0)
#1820
b11101 &
b11101 ,
b0 %
b0 +
b11110 (
b11110 .
b1000111101 $
b1000111101 *
#1850
b10001101 /
b10001101 !
1#
1)
#1870
b0 &
b0 ,
b1 (
b1 .
b101110110 $
b101110110 *
#1900
0#
0)
#1920
b11101 &
b11101 ,
b100 %
b100 +
b11100 (
b11100 .
b100011011 $
b100011011 *
1'
1-
#1950
bx /
bx !
1#
1)
#1970
b11 &
b11 ,
b1 %
b1 +
b0 (
b0 .
b110011101 $
b110011101 *
0'
0-
#2000
0#
0)
#2020
b1 &
b1 ,
b10 %
b10 +
b10 (
b10 .
b11101011 $
b11101011 *
#2050
b101010011 /
b101010011 !
1#
1)
#2070
b11101 &
b11101 ,
b1 %
b1 +
b1 (
b1 .
b11 $
b11 *
#2100
0#
0)
#2120
b1 &
b1 ,
b11100 %
b11100 +
b11111 (
b11111 .
b1101000101 $
b1101000101 *
1'
1-
#2150
b100011011 /
b100011011 !
1#
1)
#2170
b10 &
b10 ,
b11110 %
b11110 +
b1 (
b1 .
b111101010 $
b111101010 *
#2200
0#
0)
#2220
b11100 &
b11100 ,
b11 %
b11 +
b11111 (
b11111 .
b1110100110 $
b1110100110 *
0'
0-
#2250
b100011011 0
b100011011 "
b1001011101 /
b1001011101 !
1#
1)
#2270
b10 &
b10 ,
b0 (
b0 .
b11101 $
b11101 *
1'
1-
#2300
0#
0)
#2320
b100 &
b100 ,
b11111 %
b11111 +
b11110 (
b11110 .
b11100111 $
b11100111 *
#2350
bx 0
bx "
b1101000101 /
b1101000101 !
1#
1)
#2370
b11100 &
b11100 ,
b11 %
b11 +
b11 (
b11 .
b1100011011 $
b1100011011 *
0'
0-
#2400
0#
0)
#2420
b11 &
b11 ,
b0 %
b0 +
b0 (
b0 .
b110100010 $
b110100010 *
1'
1-
#2450
b1001011101 0
b1001011101 "
b10001101 /
b10001101 !
1#
1)
#2470
b1 &
b1 ,
b11111 %
b11111 +
b11111 (
b11111 .
b11011010 $
b11011010 *
0'
0-
#2500
0#
0)
#2520
b11110 &
b11110 ,
b1 %
b1 +
b11110 (
b11110 .
b100000100 $
b100000100 *
#2550
b11100111 0
b11100111 "
bx /
bx !
1#
1)
#2570
b11101 &
b11101 ,
b11100 (
b11100 .
b10011010 $
b10011010 *
#2600
0#
0)
#2620
b11100 &
b11100 ,
b11101 %
b11101 +
b11 (
b11 .
b10110010 $
b10110010 *
1'
1-
#2650
b100011011 0
b100011011 "
1#
1)
#2670
b0 %
b0 +
b0 (
b0 .
b111111001 $
b111111001 *
#2700
0#
0)
#2720
b0 &
b0 ,
b100 %
b100 +
b11101 (
b11101 .
b111000 $
b111000 *
0'
0-
#2750
b110100010 0
b110100010 "
1#
1)
#2770
b1 &
b1 ,
b11100 %
b11100 +
b11100 (
b11100 .
b1011000 $
b1011000 *
#2800
0#
0)
#2820
b0 &
b0 ,
b100 %
b100 +
b11110 (
b11110 .
b110010001 $
b110010001 *
#2850
1#
1)
#2870
b11 &
b11 ,
b10 %
b10 +
b10 (
b10 .
b1001011 $
b1001011 *
1'
1-
#2900
0#
0)
#2920
b1 &
b1 ,
b0 %
b0 +
b11101 (
b11101 .
b110011110 $
b110011110 *
#2950
bx 0
bx "
b110100010 /
b110100010 !
1#
1)
#2970
b11111 &
b11111 ,
b10 %
b10 +
b1 (
b1 .
b10101110 $
b10101110 *
0'
0-
#3000
0#
0)
#3020
b11101 &
b11101 ,
b100 %
b100 +
b11110 (
b11110 .
b1011011110 $
b1011011110 *
1'
1-
#3050
b110011110 0
b110011110 "
bx /
bx !
1#
1)
#3070
b11100 &
b11100 ,
b10 %
b10 +
b0 (
b0 .
b1011001100 $
b1011001100 *
0'
0-
#3100
0#
0)
#3120
b11 &
b11 ,
b0 %
b0 +
b10 (
b10 .
b1101001010 $
b1101001010 *
#3150
b10110010 0
b10110010 "
b110100010 /
b110100010 !
1#
1)
#3170
b10 &
b10 ,
b11111 %
b11111 +
b11101 (
b11101 .
b1011110011 $
b1011110011 *
1'
1-
#3200
0#
0)
#3220
b1 &
b1 ,
b11100 (
b11100 .
b1100010001 $
b1100010001 *
0'
0-
#3250
bx 0
bx "
b1101000101 /
b1101000101 !
1#
1)
#3270
b0 &
b0 ,
b100 %
b100 +
b110000101 $
b110000101 *
#3300
0#
0)
#3320
b11111 &
b11111 ,
b0 %
b0 +
b0 (
b0 .
b1001101111 $
b1001101111 *
#3350
b1101000101 0
b1101000101 "
b110100010 /
b110100010 !
1#
1)
#3370
b1 &
b1 ,
b11 %
b11 +
b11 (
b11 .
b11110011 $
b11110011 *
#3400
0#
0)
#3420
b11100 &
b11100 ,
b11101 %
b11101 +
b11111 (
b11111 .
b11110010 $
b11110010 *
1'
1-
#3450
b100011011 0
b100011011 "
b110011110 /
b110011110 !
1#
1)
#3470
b11111 &
b11111 ,
b11111 %
b11111 +
b1 (
b1 .
b100100110 $
b100100110 *
0'
0-
#3500
0#
0)
#3520
b11100 &
b11100 ,
b10 %
b10 +
b11111 (
b11111 .
b10010101 $
b10010101 *
#3550
b101010011 /
b101010011 !
1#
1)
#3570
b11101 &
b11101 ,
b11111 %
b11111 +
b1100100001 $
b1100100001 *
#3600
0#
0)
#3620
b0 &
b0 ,
b0 %
b0 +
b1 (
b1 .
b1001 $
b1001 *
1'
1-
#3650
b110100010 0
b110100010 "
b110100010 /
b110100010 !
1#
1)
#3670
b11110 %
b11110 +
b11 (
b11 .
b1101110010 $
b1101110010 *
#3700
0#
0)
#3720
b11111 &
b11111 ,
b10 %
b10 +
b11101 (
b11101 .
b1001010100 $
b1001010100 *
0'
0-
#3750
b11110010 0
b11110010 "
b101010011 /
b101010011 !
1#
1)
#3770
b100 %
b100 +
b0 (
b0 .
b1110011111 $
b1110011111 *
#3800
0#
0)
#3820
b11101 &
b11101 ,
b10 %
b10 +
b1 (
b1 .
b111110111 $
b111110111 *
1'
1-
#3850
b110011110 0
b110011110 "
1#
1)
#3870
b11111 %
b11111 +
b11110 (
b11110 .
b101110000 $
b101110000 *
0'
0-
#3900
0#
0)
#3920
b100 &
b100 ,
b10 %
b10 +
b100 (
b100 .
b100100111 $
b100100111 *
1'
1-
#3950
bx 0
bx "
1#
1)
#3970
b11101 &
b11101 ,
b1 %
b1 +
#4000
0#
0)
#4020
b11110 %
b11110 +
b11100 (
b11100 .
b1110010100 $
b1110010100 *
#4050
b110011110 0
b110011110 "
b1011011110 /
b1011011110 !
1#
1)
#4070
b11 &
b11 ,
b100 %
b100 +
b1100000011 $
b1100000011 *
0'
0-
#4100
0#
0)
#4120
b1 &
b1 ,
b11111 %
b11111 +
b100 (
b100 .
b1000100001 $
b1000100001 *
#4150
b111110111 0
b111110111 "
b11110010 /
b11110010 !
1#
1)
#4170
b0 &
b0 ,
b10 %
b10 +
b10 (
b10 .
b1110010001 $
b1110010001 *
1'
1-
#4200
0#
0)
#4220
b100 &
b100 ,
b11 %
b11 +
b11 (
b11 .
b100110000 $
b100110000 *
0'
0-
#4250
b100100111 0
b100100111 "
b10110010 /
b10110010 !
1#
1)
#4270
b11111 &
b11111 ,
b10 %
b10 +
b11111 (
b11111 .
b1001101111 $
b1001101111 *
1'
1-
#4300
0#
0)
#4320
b10 &
b10 ,
b100 %
b100 +
b11100 (
b11100 .
b1110000001 $
b1110000001 *
#4350
b101010011 0
b101010011 "
b100100111 /
b100100111 !
1#
1)
#4370
b0 &
b0 ,
b11 %
b11 +
b1011001110 $
b1011001110 *
#4400
0#
0)
#4420
b11 &
b11 ,
b11111 %
b11111 +
b11111 (
b11111 .
b1100 $
b1100 *
0'
0-
#4450
b10110010 0
b10110010 "
b11110010 /
b11110010 !
1#
1)
#4470
b11110 %
b11110 +
b0 (
b0 .
b111010010 $
b111010010 *
1'
1-
#4500
0#
0)
#4520
b11110 &
b11110 ,
b1 %
b1 +
b11100 (
b11100 .
b1011110000 $
b1011110000 *
0'
0-
#4550
b1011011110 0
b1011011110 "
b111110111 /
b111110111 !
1#
1)
#4570
b1001000111 $
b1001000111 *
1'
1-
#4600
0#
0)
#4620
b0 &
b0 ,
b0 %
b0 +
b1000111101 $
b1000111101 *
0'
0-
#4650
b110100010 0
b110100010 "
b110100010 /
b110100010 !
1#
1)
#4670
b1 %
b1 +
b100 (
b100 .
b1101010 $
b1101010 *
1'
1-
#4700
0#
0)
#4720
b11110 &
b11110 ,
b11111 %
b11111 +
b11111 (
b11111 .
b110011110 $
b110011110 *
0'
0-
#4750
b1011011110 0
b1011011110 "
b11110010 /
b11110010 !
1#
1)
#4770
b11100 &
b11100 ,
b100 %
b100 +
b11 (
b11 .
b10111101 $
b10111101 *
#4800
0#
0)
#4820
b11 &
b11 ,
b11100 %
b11100 +
b100 (
b100 .
b11001001 $
b11001001 *
#4850
b10110010 0
b10110010 "
b1110000001 /
b1110000001 !
1#
1)
#4870
b11100 &
b11100 ,
b11 %
b11 +
b1 (
b1 .
b1010111 $
b1010111 *
1'
1-
#4900
0#
0)
#4920
b11101 &
b11101 ,
b0 %
b0 +
b0 (
b0 .
b1100111011 $
b1100111011 *
0'
0-
#4950
b110011110 0
b110011110 "
b110100010 /
b110100010 !
1#
1)
#4970
b11111 &
b11111 ,
b1 %
b1 +
b11110 (
b11110 .
b101111101 $
b101111101 *
#5000
0#
0)
#5020
b10 &
b10 ,
b11100 %
b11100 +
b1001101000 $
b1001101000 *
1'
1-
