COA/A2/1/ALU.v
/*
------------------------------------------------------
            Praveen Kumar Gupta  -  16CO235
            Durvesh Bhalekar     -  16CO210
------------------------------------------------------
           				1-bit ALU
------------------------------------------------------

*/
module multiplexer1(A,B,Y,invert);
	input A,B;
	input invert;
	output Y;
	
	not(invert_bar,invert);
	and(Y1,A,invert_bar);
	and(Y2,B,invert);
	or(Y,Y1,Y2);
	
endmodule

//half-adder

module full_adder(S,C,X,Y,Z);
	input X,Y,Z;
	output S,C;
	
	xor(S,X,Y,Z);
	and(C1,X,Y);
	and(C2,Y,Z);
	and(C3,X,Z);
	or(C,C1,C2,C3);
	
endmodule

//Multiplexer2 --> 4:1 MUX

module multiplexer2(A,B,C,D,op,result);
	input A,B,C,D;
	input [0:1]op;
	output result;
	
	not(op0_bar,op[0]);
	not(op1_bar,op[1]);
	
	and(result1,A,op0_bar,op1_bar);
	and(result2,B,op0_bar,op[1]);
	and(result3,C,op[0],op1_bar);
	and(result4,D,op[0],op[1]);
	or(result,result1,result2,result3,result4);
	
endmodule

//Main ALU code
//flag2 to check whether the first input (A) is greater than second (B)
//flag2 will be 1 if first input (A) is greater than second input (B)

module ALU(A,B,Less,A_invert,B_invert,carry_in,result,carry,op,flag1,flag2);
	input A,B,Less,A_invert,B_invert,carry_in;
	input [0:1]op;
	output result,carry,flag2,flag1;
	
	not(A_bar,A);
	not(B_bar,B);
	multiplexer1 M1(.A(A),.B(A_bar),.Y(R1),.invert(A_invert));
	multiplexer1 M2(.A(B),.B(B_bar),.Y(R2),.invert(B_invert));
	and(In1,R1,R2);
	or(In2,R1,R2);
	full_adder F1(.S(R3),.C(carry),.X(carry_in),.Y(R1),.Z(R2));
    multiplexer2 M3(.A(In1),.B(In2),.C(R3),.D(Less),.op(op),.result(result));
	not(B_bar,B);
	not(flag1,result);
    and(flag2,B_bar,A);
	
endmodule

COA/A2/1/t_ALU.v
/*
------------------------------------------------------
            Praveen Kumar Gupta  -  16CO235
            Durvesh Bhalekar     -  16CO210
------------------------------------------------------
           		Testbench for 1-bit ALU
------------------------------------------------------

*/
`timescale 1ns/10ps

module t_ALU;
	wire result,carry,flag2,flag1;
	reg  A,B,Less,A_invert,B_invert,carry_in;
	reg [0:1]op;
	
	ALU MM1(.A(A),.B(B),.Less(Less),.A_invert(A_invert),.B_invert(B_invert),.carry_in(carry_in),.result(result),.carry(carry),.op(op),.flag1(flag1),.flag2(flag2));
	
	initial
	begin
		$dumpfile("t_ALU.vcd");
		$dumpvars(0,t_ALU);
		
		//for AND and OR
		
		carry_in=1'b0;
		A_invert=1'b0;
		B_invert=1'b0;
		
		A=1'b0;
		B=1'b0;
		
		$display(" \ncarry_in = %b , A_invert = %b , B_invert = %b , A = %b , B = %b ,flag1 = %b , flag2 = %b",carry_in,A_invert,B_invert,A,B,flag1,flag2);
		#1;
		$display(" ------------------------------------------------------------------------------------------ ");
		#1
		
		op=2'b00;
		$display("AND result = %b , op = %b \n",result,op);
		#10;
		
		op=2'b01;
		$display("OR result = %b , op = %b \n",result,op);
		#10;
		
		op=2'b10;
		$display("ADDITION result = %b , op = %b \n",result,op);
		#10;
		
		A=1'b0;
		B=1'b1;
		
		$display(" \ncarry_in = %b , A_invert = %b , B_invert = %b , A = %b , B = %b ,flag1 = %b , flag2 = %b",carry_in,A_invert,B_invert,A,B,flag1,flag2);
		#1;
		$display("-------------------------------------------------------------------------------------------- ");
		#1
		
		op=2'b00;
		$display("AND result = %b , op = %b \n",result, op);
		#10;
		
		op=2'b01;
		$display("OR result = %b , op = %b \n",result,op);
		#10;
		
		op=2'b10;
		$display("ADDITION result = %b , op = %b \n",result,op);
		#10;
		
		A=1'b1;
		B=1'b0;
		
 		$display(" \ncarry_in = %b , A_invert = %b , B_invert = %b , A = %b , B = %b ,flag1 = %b , flag2 = %b",carry_in,A_invert,B_invert,A,B,flag1,flag2);
		#1;
		$display("----------------------------------------------------------------------------------------- ");
		#1
		
		op=2'b00;
		$display("AND result = %b , op = %b \n",result,op);
		#10;
		
		op=2'b01;
		$display("OR result = %b , op = %b \n",result,op);
		#10;
		
		op=2'b10;
		$display("ADDITION result = %b , op = %b\n",result,op);
		#10;
		
		A=1'b1;
		B=1'b1;
		
		$display(" \ncarry_in = %b , A_invert = %b , B_invert = %b , A = %b , B = %b ,flag1 = %b , flag2 = %b",carry_in,A_invert,B_invert,A,B,flag1,flag2);
		#1;
		$display("----------------------------------------------------------------------------------------------- ");
		#1
		
		op=2'b00;
		$display("AND result = %b , op = %b\n",result,op);
		#10;
		
		op=2'b01;
		$display("OR result = %b , op = %b\n",result,op);
		#10;
		
		op=2'b10;
		$display("ADDITION result = %b , op = %b\n",result,op);
		#10;
		
		//---------------------------------------------------------------------------------------------------------------------------------
		//For NOR and NAND
		
		carry_in=1'b1;
		A_invert=1'b1;
		B_invert=1'b1;
		
		A=1'b0;
		B=1'b0;
		
		$display(" \n carry_in = %b , A_invert = %b , B_invert = %b , A = %b , B = %b ,flag1 = %b , flag2 = %b",carry_in,A_invert,B_invert,A,B,flag1,flag2);
		#1;
		$display(" ----------------------------------------------------------------------------------------------- ");
		#1
		
		op=2'b00;
		$display("NOR result = %b , op = %b \n",result,op);
		#10;
		
		op=2'b01;
		$display("NAND result = %b , op = %b \n",result,op);
		#10;
		
		
		A=1'b0;
		B=1'b1;
		
		$display(" \n carry_in = %b , A_invert = %b , B_invert = %b , A = %b , B = %b ,flag1 = %b , flag2 = %b",carry_in,A_invert,B_invert,A,B,flag1,flag2);
		#1;
		$display(" --------------------------------------------------------------------------------------------- ");
		#1
		
		op=2'b00;
		$display("NOR result = %b , op = %b \n",result,op);
		#10;
		
		op=2'b01;
		$display("NAND result = %b , op = %b \n",result,op);
		#10;
		
		
		A=1'b1;
		B=1'b0;
		
		$display(" \n carry_in = %b , A_invert = %b , B_invert = %b , A = %b , B = %b ,flag1 = %b , flag2 = %b",carry_in,A_invert,B_invert,A,B,flag1,flag2);
		#1;
		$display(" ------------------------------------------------------------------------------------------- ");
		#1
		
		op=2'b00;
		$display("NOR result = %b , op = %b \n",result,op);
		#10;
		
		op=2'b01;
		$display("NAND result = %b , op = %b \n",result,op);
		#10;
		
		A=1'b1;
		B=1'b1;
		
		$display(" \n carry_in = %b , A_invert = %b , B_invert = %b , A = %b , B = %b ,flag1 = %b , flag2 = %b",carry_in,A_invert,B_invert,A,B,flag1,flag2);
		#1;
		$display(" ------------------------------------------------------------------------------------------- ");
		#1
		
		op=2'b00;
		$display("NOR result = %b , op =%b \n",result,op);
		#10;
		
		op=2'b01;
		$display("NAND result = %b , op = %b \n",result,op);
		#10;
		
		
		//--------------------------------------------------------------------------------------------------------------------------------
		
		A_invert=1'b0;
		op=2'b10;
		
		A=1'b0;
		B=1'b0;
		
		$display(" \n carry_in = %b , A_invert = %b , B_invert = %b , A = %b , B = %b ,flag1 = %b , flag2 = %b",carry_in,A_invert,B_invert,A,B,flag1,flag2);
		#1;
		$display("---------------------------------------------------------------------------------------------");
		#1
		
		$display("SUBTRACTION result = %b , op = %b \n",result,op);
		#10;
		
		A=1'b0;
		B=1'b1;
		
		$display(" \n carry_in = %b , A_invert = %b , B_invert = %b , A = %b , B = %b ,flag1 = %b , flag2 = %b",carry_in,A_invert,B_invert,A,B,flag1,flag2);
		#1;
		$display("---------------------------------------------------------------------------------------------");
		#1
		
		$display("SUBTRACTION result = %b , op = %b \n",result,op);
		#10;
		
		A=1'b1;
		B=1'b0;
		
		$display(" \n carry_in = %b , A_invert = %b , B_invert = %b , A = %b , B = %b ,flag1 = %b , flag2 = %b",carry_in,A_invert,B_invert,A,B,flag1,flag2);
		#1;
		$display("---------------------------------------------------------------------------------------------");
		#1
		
		$display("SUBTRACTION result = %b , op = %b \n",result,op);
		#10;
		
		A=1'b1;
		B=1'b1;
		
		$display(" \n carry_in = %b , A_invert = %b , B_invert = %b , A = %b , B = %b ,flag1 = %b , flag2 = %b",carry_in,A_invert,B_invert,A,B,flag1,flag2);
		#1;
		$display("---------------------------------------------------------------------------------------------");
		#1
		
		$display("SUBTRACTION result = %b , op = %b \n",result,op);
		
		
	end
	initial #1000 $finish;
endmodule

COA/A2/1/t_ALU.vcd
$date
	Tue Oct 31 21:58:39 2017
$end
$version
	Icarus Verilog
$end
$timescale
	10ps
$end
$scope module t_ALU $end
$var wire 1 ! carry $end
$var wire 1 " flag1 $end
$var wire 1 # flag2 $end
$var wire 1 $ result $end
$var reg 1 % A $end
$var reg 1 & A_invert $end
$var reg 1 ' B $end
$var reg 1 ( B_invert $end
$var reg 1 ) Less $end
$var reg 1 * carry_in $end
$var reg 2 + op [0:1] $end
$scope module MM1 $end
$var wire 1 , A $end
$var wire 1 - A_bar $end
$var wire 1 . A_invert $end
$var wire 1 / B $end
$var wire 1 0 B_bar $end
$var wire 1 1 B_invert $end
$var wire 1 2 In1 $end
$var wire 1 3 In2 $end
$var wire 1 4 Less $end
$var wire 1 5 R1 $end
$var wire 1 6 R2 $end
$var wire 1 7 R3 $end
$var wire 1 ! carry $end
$var wire 1 8 carry_in $end
$var wire 1 " flag1 $end
$var wire 1 # flag2 $end
$var wire 2 9 op [0:1] $end
$var wire 1 $ result $end
$scope module M1 $end
$var wire 1 , A $end
$var wire 1 - B $end
$var wire 1 5 Y $end
$var wire 1 : Y1 $end
$var wire 1 ; Y2 $end
$var wire 1 . invert $end
$var wire 1 < invert_bar $end
$upscope $end
$scope module M2 $end
$var wire 1 / A $end
$var wire 1 0 B $end
$var wire 1 6 Y $end
$var wire 1 = Y1 $end
$var wire 1 > Y2 $end
$var wire 1 1 invert $end
$var wire 1 ? invert_bar $end
$upscope $end
$scope module F1 $end
$var wire 1 ! C $end
$var wire 1 @ C1 $end
$var wire 1 A C2 $end
$var wire 1 B C3 $end
$var wire 1 7 S $end
$var wire 1 8 X $end
$var wire 1 5 Y $end
$var wire 1 6 Z $end
$upscope $end
$scope module M3 $end
$var wire 1 2 A $end
$var wire 1 3 B $end
$var wire 1 7 C $end
$var wire 1 4 D $end
$var wire 2 C op [0:1] $end
$var wire 1 D op0_bar $end
$var wire 1 E op1_bar $end
$var wire 1 $ result $end
$var wire 1 F result1 $end
$var wire 1 G result2 $end
$var wire 1 H result3 $end
$var wire 1 I result4 $end
$upscope $end
$upscope $end
$upscope $end
$enddefinitions $end
#0
$dumpvars
xI
0H
0G
0F
xE
xD
bx C
0B
0A
0@
1?
0>
0=
1<
0;
0:
bx 9
08
07
06
05
x4
03
02
01
10
0/
0.
1-
0,
bx +
0*
x)
0(
0'
0&
0%
x$
0#
x"
0!
$end
#200
1"
0$
1D
1E
0I
b0 +
b0 9
b0 C
#1200
0E
b1 +
b1 9
b1 C
#2200
0D
1E
b10 +
b10 9
b10 C
#3200
0"
1$
1H
17
13
16
00
1=
1'
1/
#3400
1"
0$
1D
0H
b0 +
b0 9
b0 C
#4400
0"
1$
0E
1G
b1 +
b1 9
b1 C
#5400
0"
1H
1$
0D
1E
0G
b10 +
b10 9
b10 C
#6400
1#
06
15
10
0=
0-
1:
0'
0/
1%
1,
#6600
1"
0$
1D
0H
b0 +
b0 9
b0 C
#7600
0"
1$
0E
1G
b1 +
b1 9
b1 C
#8600
0"
1H
1$
0D
1E
0G
b10 +
b10 9
b10 C
#9600
1"
0$
0H
1!
07
1A
12
0#
16
00
1=
1'
1/
#9800
0"
1$
1F
1D
b0 +
b0 9
b0 C
#10800
0F
0E
1G
b1 +
b1 9
b1 C
#11800
1"
0$
0D
1E
0G
b10 +
b10 9
b10 C
#12800
1!
0"
1A
13
12
1$
1>
16
1;
15
1H
10
0=
1-
0:
0?
0<
17
1@
1B
0'
0/
0%
0,
1(
11
1&
1.
1*
18
#13000
0"
1F
1$
1D
0H
b0 +
b0 9
b0 C
#14000
0F
0E
1G
b1 +
b1 9
b1 C
#15000
07
0A
0B
02
06
0>
00
1'
1/
#15200
1"
0$
1E
0G
b0 +
b0 9
b0 C
#16200
0"
1$
0E
1G
b1 +
b1 9
b1 C
#17200
1B
0@
16
05
1#
1>
0;
10
0-
0'
0/
1%
1,
#17400
1"
0$
1E
0G
b0 +
b0 9
b0 C
#18400
0"
1$
0E
1G
b1 +
b1 9
b1 C
#19400
1"
0$
0!
0G
17
0B
03
06
0#
0>
00
1'
1/
#19600
1E
b0 +
b0 9
b0 C
#20600
0E
b1 +
b1 9
b1 C
#21600
1!
1"
07
1B
13
0$
16
0H
1>
0D
1E
10
1-
1<
0'
0/
0%
0,
b10 +
b10 9
b10 C
0&
0.
#22800
0"
1$
1H
0!
17
0B
03
06
0>
00
1'
1/
#24000
0"
1$
1A
1B
12
1H
1!
16
17
1@
13
1#
1>
15
10
0-
1:
0'
0/
1%
1,
#25200
1"
0$
0H
07
0A
0B
02
06
0#
0>
00
1'
1/
