COA/A1/2/dec.v
/*
------------------------------------------------------
            Praveen Kumar Gupta  -  16CO235
            Durvesh Bhalekar     -  16CO210
------------------------------------------------------
                    4 x 16 Decoder
------------------------------------------------------

*/
module DEC(a,b,c,d,out);
    input a,b,c,d;
    output reg [15:0] out;
    always @(a,b,c,d)
        begin
            assign out[0] = ~a & ~b & ~c & ~d;
            assign out[1] = ~a & ~b & ~c & d;
            assign out[2] = ~a & ~b & c & ~d;
            assign out[3] = ~a & ~b & c & d;
            assign out[4] = ~a & b & ~c & ~d;
            assign out[5] = ~a & b & ~c & d;
            assign out[6] = ~a & b & c & ~d;
            assign out[7] = ~a & b & c & d;
            assign out[8] = a & ~b & ~c & ~d;
            assign out[9] = a & ~b & ~c & d;
            assign out[10] = a & ~b & c & ~d;
            assign out[11] = a & ~b & c & d;
            assign out[12] = a & b & ~c & ~d;
            assign out[13] = a & b & ~c & d;
            assign out[14] = a & b & c & ~d;
            assign out[15] = a & b & c & d;            
        end
        /*begin
            if(c==1'b0 && d==1'b0)
                begin
                    assign out[3]=a&b;
                    assign out[2]=a&~b;
                    assign out[1]=~a&b;
                    assign out[0]=~a&~b;
                     
                end
            else if(c==1'b1 && d==1'b0)
                begin
                    assign out[7]=a&b;
                    assign out[6]=a&~b;
                    assign out[5]=~a&b;
                    assign out[4]=~a&~b;
                end
            else if(c==1'b0 && d==1'b1)
                begin
                    assign out[11]=a&b;
                    assign out[10]=a&~b;
                    assign out[9]=~a&b;
                    assign out[8]=~a&~b;
                end
            else if(c==1'b1 && d==1'b1)
                begin
                    assign out[15]=a&b;
                    assign out[14]=a&~b;
                    assign out[13]=~a&b;
                    assign out[12]=~a&~b;
                end
        end*/
endmodule
/*
module twoFour(input wire a,b,En,output reg[3:0] out);

    initial    
        if(En==1'b1)
            begin
                assign out[3]=a&b;
                assign out[2]=a&~b;
                assign out[1]=~a&b;
                assign out[0]=~a&~b;              
            end
endmodule
*/

COA/A1/2/t_dec.v
/*
------------------------------------------------------
            Praveen Kumar Gupta  -  16CO235
            Durvesh Bhalekar     -  16CO210
------------------------------------------------------
              Testbench for 4 x 16 Decoder
------------------------------------------------------

*/

`timescale 1ns/100ps
module dec();
    wire [15:0]out;
    reg [3:0]inp;
    DEC myDec(inp[3],inp[2],inp[1],inp[0],out);
    initial 
    begin
        $dumpfile("dec.vcd");
        $dumpvars(0,dec);
        $display("A B C D |\tOutput\n-------------------------");     

        inp=4'b0000;
        repeat(15)
            #10 inp=inp+1'b1;   
        #10;
        $finish;
    end

    initial
        begin
            $monitor("%b %b %b %b| %b ",inp[3],inp[2],inp[1],inp[0],out);
        end
endmodule

COA/A1/2/dec.vcd
$date
	Tue Oct 17 21:08:16 2017
$end
$version
	Icarus Verilog
$end
$timescale
	100ps
$end
$scope module dec $end
$var wire 16 ! out [15:0] $end
$var reg 4 " inp [3:0] $end
$scope module myDec $end
$var wire 1 # a $end
$var wire 1 $ b $end
$var wire 1 % c $end
$var wire 1 & d $end
$var reg 16 ' out [15:0] $end
$upscope $end
$upscope $end
$enddefinitions $end
#0
$dumpvars
b1 '
0&
0%
0$
0#
b0 "
b1 !
$end
#100
b10 '
b10 !
1&
b1 "
#200
b100 !
b100 '
1%
0&
b10 "
#300
b1000 !
b1000 '
1&
b11 "
#400
b10000 !
b10000 '
1$
0%
0&
b100 "
#500
b100000 !
b100000 '
1&
b101 "
#600
b1000000 !
b1000000 '
1%
0&
b110 "
#700
b10000000 !
b10000000 '
1&
b111 "
#800
b100000000 !
b100000000 '
1#
0$
0%
0&
b1000 "
#900
b1000000000 !
b1000000000 '
1&
b1001 "
#1000
b10000000000 !
b10000000000 '
1%
0&
b1010 "
#1100
b100000000000 !
b100000000000 '
1&
b1011 "
#1200
b1000000000000 !
b1000000000000 '
1$
0%
0&
b1100 "
#1300
b10000000000000 !
b10000000000000 '
1&
b1101 "
#1400
b100000000000000 !
b100000000000000 '
1%
0&
b1110 "
#1500
b1000000000000000 !
b1000000000000000 '
1&
b1111 "
